Metadata-Version: 2.4
Name: llama-index-llms-you
Version: 0.4.1
Summary: llama-index LLM integration with You.com's conversational Smart and Research APIs
Author: You-OpenSource
License-Expression: MIT
License-File: LICENSE
Requires-Python: <4.0,>=3.9
Requires-Dist: llama-index-core<0.15,>=0.13.0
Requires-Dist: sseclient-py<2,>=1.8.0
